pymultienv/__init__.py
pymultienv/me.py
pymultienv/static.py
pymultienv-0.0.5.dist-info/LICENSE
pymultienv-0.0.5.dist-info/METADATA
pymultienv-0.0.5.dist-info/WHEEL
pymultienv-0.0.5.dist-info/entry_points.txt
pymultienv-0.0.5.dist-info/top_level.txt
pymultienv-0.0.5.dist-info/RECORD
