Metadata-Version: 2.1
Name: pymultienv
Version: 0.0.5
Summary: pymultienv is a command to help you deal with multiple python environments
Home-page: https://veltzer.github.io/pymultienv
Download-URL: https://github.com/veltzer/pymultienv
Author: Mark Veltzer
Author-email: mark.veltzer@gmail.com
Maintainer: Mark Veltzer
Maintainer-email: mark.veltzer@gmail.com
License: MIT
Keywords: git,python,repositories,multiple
Platform: python3
Classifier: Development Status :: 4 - Beta
Classifier: Environment :: Console
Classifier: Operating System :: OS Independent
Classifier: Programming Language :: Python
Classifier: Programming Language :: Python :: 3
Classifier: Programming Language :: Python :: 3 :: Only
Classifier: Programming Language :: Python :: 3.11
Classifier: Topic :: Utilities
Classifier: License :: OSI Approved :: MIT License
License-File: LICENSE
Requires-Dist: gitpython
Requires-Dist: pyfakeuse
